{
  "symbols": {
    "s_hA9UPaY8sNQ": {
      "origin": "../node_modules/@builder.io/qwik-city/index.qwik.mjs",
      "displayName": "Link_component_a_onClick",
      "canonicalFilename": "s_ha9upay8snq",
      "hash": "hA9UPaY8sNQ",
      "ctxKind": "event",
      "ctxName": "onClick$",
      "captures": true,
      "parent": "s_mYsiJcA4IBc"
    },
    "s_skxgNVWVOT8": {
      "origin": "../node_modules/@builder.io/qwik-city/index.qwik.mjs",
      "displayName": "Link_component_a_onMouseOver",
      "canonicalFilename": "s_skxgnvwvot8",
      "hash": "skxgNVWVOT8",
      "ctxKind": "event",
      "ctxName": "onMouseOver$",
      "captures": false,
      "parent": "s_mYsiJcA4IBc"
    },
    "s_PwNkd8FfaIM": {
      "origin": "routes/flower/index.tsx",
      "displayName": "flower_component__Fragment_input_onInput",
      "canonicalFilename": "s_pwnkd8ffaim",
      "hash": "PwNkd8FfaIM",
      "ctxKind": "event",
      "ctxName": "onInput$",
      "captures": true,
      "parent": "s_zGuTamIAxMs"
    },
    "s_uVE5iM9H73c": {
      "origin": "../node_modules/@builder.io/qwik-city/index.qwik.mjs",
      "displayName": "Link_component_a_onQVisible",
      "canonicalFilename": "s_uve5im9h73c",
      "hash": "uVE5iM9H73c",
      "ctxKind": "event",
      "ctxName": "onQVisible$",
      "captures": false,
      "parent": "s_mYsiJcA4IBc"
    },
    "s_AaAlzKH0KlQ": {
      "origin": "../node_modules/@builder.io/qwik-city/index.qwik.mjs",
      "displayName": "QwikCity_component_useWatch",
      "canonicalFilename": "s_aaalzkh0klq",
      "hash": "AaAlzKH0KlQ",
      "ctxKind": "function",
      "ctxName": "useWatch$",
      "captures": true,
      "parent": "s_z1nvHyEppoI"
    },
    "s_qlbHqLk9LmU": {
      "origin": "routes/flower/index.tsx",
      "displayName": "flower_component_useClientEffect",
      "canonicalFilename": "s_qlbhqlk9lmu",
      "hash": "qlbHqLk9LmU",
      "ctxKind": "function",
      "ctxName": "useClientEffect$",
      "captures": true,
      "parent": "s_zGuTamIAxMs"
    },
    "s_H1DCWNWGDs0": {
      "origin": "root.tsx",
      "displayName": "root_component",
      "canonicalFilename": "s_h1dcwnwgds0",
      "hash": "H1DCWNWGDs0",
      "ctxKind": "function",
      "ctxName": "component$",
      "captures": false
    },
    "s_USHQYhRQTrM": {
      "origin": "routes/index .tsx",
      "displayName": "index__component",
      "canonicalFilename": "s_ushqyhrqtrm",
      "hash": "USHQYhRQTrM",
      "ctxKind": "function",
      "ctxName": "component$",
      "captures": false
    },
    "s_VkTVgkSdmLs": {
      "origin": "components/router-head/router-head.tsx",
      "displayName": "RouterHead_component",
      "canonicalFilename": "s_vktvgksdmls",
      "hash": "VkTVgkSdmLs",
      "ctxKind": "function",
      "ctxName": "component$",
      "captures": false
    },
    "s_c1z6q2id8HY": {
      "origin": "routes/layout.tsx",
      "displayName": "layout_component",
      "canonicalFilename": "s_c1z6q2id8hy",
      "hash": "c1z6q2id8HY",
      "ctxKind": "function",
      "ctxName": "component$",
      "captures": false
    },
    "s_mYsiJcA4IBc": {
      "origin": "../node_modules/@builder.io/qwik-city/index.qwik.mjs",
      "displayName": "Link_component",
      "canonicalFilename": "s_mysijca4ibc",
      "hash": "mYsiJcA4IBc",
      "ctxKind": "function",
      "ctxName": "component$",
      "captures": false
    },
    "s_nd8yk3KO22c": {
      "origin": "../node_modules/@builder.io/qwik-city/index.qwik.mjs",
      "displayName": "RouterOutlet_component",
      "canonicalFilename": "s_nd8yk3ko22c",
      "hash": "nd8yk3KO22c",
      "ctxKind": "function",
      "ctxName": "component$",
      "captures": false
    },
    "s_z1nvHyEppoI": {
      "origin": "../node_modules/@builder.io/qwik-city/index.qwik.mjs",
      "displayName": "QwikCity_component",
      "canonicalFilename": "s_z1nvhyeppoi",
      "hash": "z1nvHyEppoI",
      "ctxKind": "function",
      "ctxName": "component$",
      "captures": false
    },
    "s_zGuTamIAxMs": {
      "origin": "routes/flower/index.tsx",
      "displayName": "flower_component",
      "canonicalFilename": "s_zgutamiaxms",
      "hash": "zGuTamIAxMs",
      "ctxKind": "function",
      "ctxName": "component$",
      "captures": false
    },
    "s_fMUXVKmpTMY": {
      "origin": "routes/flower/index.tsx",
      "displayName": "flower_component_useStylesScoped",
      "canonicalFilename": "s_fmuxvkmptmy",
      "hash": "fMUXVKmpTMY",
      "ctxKind": "function",
      "ctxName": "useStylesScoped$",
      "captures": false,
      "parent": "s_zGuTamIAxMs"
    }
  },
  "mapping": {
    "s_hA9UPaY8sNQ": "q-dac90a0a.js",
    "s_skxgNVWVOT8": "q-dac90a0a.js",
    "s_PwNkd8FfaIM": "q-076d2705.js",
    "s_uVE5iM9H73c": "q-dac90a0a.js",
    "s_AaAlzKH0KlQ": "q-d000eb4e.js",
    "s_qlbHqLk9LmU": "q-076d2705.js",
    "s_H1DCWNWGDs0": "q-27f51f89.js",
    "s_USHQYhRQTrM": "q-67f1f502.js",
    "s_VkTVgkSdmLs": "q-7ffe6650.js",
    "s_c1z6q2id8HY": "q-88680ef0.js",
    "s_mYsiJcA4IBc": "q-dac90a0a.js",
    "s_nd8yk3KO22c": "q-503d618b.js",
    "s_z1nvHyEppoI": "q-d000eb4e.js",
    "s_zGuTamIAxMs": "q-076d2705.js",
    "s_fMUXVKmpTMY": "q-076d2705.js"
  },
  "bundles": {
    "q-066c1a0e.js": {
      "size": 424,
      "imports": [
        "q-627075b9.js"
      ],
      "dynamicImports": [
        "q-5b8568a1.js",
        "q-66332abf.js",
        "q-88e494a7.js",
        "q-97414cd3.js"
      ],
      "origins": [
        "@qwik-city-plan"
      ]
    },
    "q-076d2705.js": {
      "size": 2511,
      "imports": [
        "q-27f51f89.js",
        "q-627075b9.js"
      ],
      "origins": [
        "src/entry_flower.js",
        "src/routes/flower/flower.css?used&inline",
        "src/s_fmuxvkmptmy.js",
        "src/s_pwnkd8ffaim.js",
        "src/s_qlbhqlk9lmu.js",
        "src/s_zgutamiaxms.js"
      ],
      "symbols": [
        "s_fMUXVKmpTMY",
        "s_PwNkd8FfaIM",
        "s_qlbHqLk9LmU",
        "s_zGuTamIAxMs"
      ]
    },
    "q-1dd5e43f.js": {
      "size": 2536,
      "origins": [
        "node_modules/@builder.io/qwik-city/service-worker.mjs",
        "src/routes/service-worker.js"
      ]
    },
    "q-27f51f89.js": {
      "size": 4159,
      "imports": [
        "q-627075b9.js"
      ],
      "dynamicImports": [
        "q-503d618b.js",
        "q-7ffe6650.js",
        "q-d000eb4e.js",
        "q-dac90a0a.js"
      ],
      "origins": [
        "node_modules/@builder.io/qwik-city/index.qwik.mjs",
        "src/components/router-head/router-head.js",
        "src/entry_root.js",
        "src/s_h1dcwnwgds0.js"
      ],
      "symbols": [
        "s_H1DCWNWGDs0"
      ]
    },
    "q-3bdcf998.js": {
      "size": 58,
      "imports": [
        "q-627075b9.js"
      ]
    },
    "q-503d618b.js": {
      "size": 269,
      "imports": [
        "q-27f51f89.js",
        "q-627075b9.js"
      ],
      "origins": [
        "src/entry_RouterOutlet.js",
        "src/s_nd8yk3ko22c.js"
      ],
      "symbols": [
        "s_nd8yk3KO22c"
      ]
    },
    "q-5b8568a1.js": {
      "size": 185,
      "imports": [
        "q-627075b9.js"
      ],
      "dynamicImports": [
        "q-67f1f502.js"
      ],
      "origins": [
        "src/routes/index .js"
      ]
    },
    "q-627075b9.js": {
      "size": 40502,
      "dynamicImports": [
        "q-27f51f89.js"
      ],
      "origins": [
        "\u0000vite/preload-helper",
        "node_modules/@builder.io/qwik/core.min.mjs",
        "src/global.css",
        "src/root.js"
      ]
    },
    "q-66332abf.js": {
      "size": 128,
      "imports": [
        "q-627075b9.js"
      ],
      "dynamicImports": [
        "q-1dd5e43f.js"
      ],
      "origins": [
        "@qwik-city-entries"
      ]
    },
    "q-67f1f502.js": {
      "size": 151,
      "imports": [
        "q-627075b9.js"
      ],
      "origins": [
        "src/entry_index_.js",
        "src/s_ushqyhrqtrm.js"
      ],
      "symbols": [
        "s_USHQYhRQTrM"
      ]
    },
    "q-7ffe6650.js": {
      "size": 878,
      "imports": [
        "q-27f51f89.js",
        "q-627075b9.js"
      ],
      "origins": [
        "src/entry_RouterHead.js",
        "src/s_vktvgksdmls.js"
      ],
      "symbols": [
        "s_VkTVgkSdmLs"
      ]
    },
    "q-88680ef0.js": {
      "size": 159,
      "imports": [
        "q-627075b9.js"
      ],
      "origins": [
        "src/entry_layout.js",
        "src/s_c1z6q2id8hy.js"
      ],
      "symbols": [
        "s_c1z6q2id8HY"
      ]
    },
    "q-88e494a7.js": {
      "size": 192,
      "imports": [
        "q-627075b9.js"
      ],
      "dynamicImports": [
        "q-076d2705.js"
      ],
      "origins": [
        "src/routes/flower/index.js"
      ]
    },
    "q-97414cd3.js": {
      "size": 158,
      "imports": [
        "q-627075b9.js"
      ],
      "dynamicImports": [
        "q-88680ef0.js"
      ],
      "origins": [
        "src/routes/layout.js"
      ]
    },
    "q-d000eb4e.js": {
      "size": 1489,
      "imports": [
        "q-27f51f89.js",
        "q-627075b9.js"
      ],
      "dynamicImports": [
        "q-066c1a0e.js"
      ],
      "origins": [
        "@builder.io/qwik/build",
        "src/entry_QwikCity.js",
        "src/s_aaalzkh0klq.js",
        "src/s_z1nvhyeppoi.js"
      ],
      "symbols": [
        "s_AaAlzKH0KlQ",
        "s_z1nvHyEppoI"
      ]
    },
    "q-dac90a0a.js": {
      "size": 886,
      "imports": [
        "q-27f51f89.js",
        "q-627075b9.js"
      ],
      "origins": [
        "src/entry_Link.js",
        "src/s_ha9upay8snq.js",
        "src/s_mysijca4ibc.js",
        "src/s_skxgnvwvot8.js",
        "src/s_uve5im9h73c.js"
      ],
      "symbols": [
        "s_hA9UPaY8sNQ",
        "s_mYsiJcA4IBc",
        "s_skxgNVWVOT8",
        "s_uVE5iM9H73c"
      ]
    }
  },
  "injections": [
    {
      "tag": "link",
      "location": "head",
      "attributes": {
        "rel": "stylesheet",
        "href": "/build/q-1251914f.css"
      }
    }
  ],
  "version": "1",
  "options": {
    "target": "client",
    "buildMode": "production",
    "forceFullBuild": true,
    "entryStrategy": {
      "type": "smart"
    }
  },
  "platform": {
    "qwik": "0.11.1",
    "vite": "",
    "rollup": "2.78.1",
    "env": "node",
    "os": "linux",
    "node": "16.18.1"
  }
}