{
  "symbols": {
    "s_hA9UPaY8sNQ": {
      "origin": "../node_modules/@builder.io/qwik-city/index.qwik.mjs",
      "displayName": "Link_component_a_onClick",
      "canonicalFilename": "s_ha9upay8snq",
      "hash": "hA9UPaY8sNQ",
      "ctxKind": "event",
      "ctxName": "onClick$",
      "captures": true,
      "parent": "s_mYsiJcA4IBc"
    },
    "s_skxgNVWVOT8": {
      "origin": "../node_modules/@builder.io/qwik-city/index.qwik.mjs",
      "displayName": "Link_component_a_onMouseOver",
      "canonicalFilename": "s_skxgnvwvot8",
      "hash": "skxgNVWVOT8",
      "ctxKind": "event",
      "ctxName": "onMouseOver$",
      "captures": false,
      "parent": "s_mYsiJcA4IBc"
    },
    "s_uVE5iM9H73c": {
      "origin": "../node_modules/@builder.io/qwik-city/index.qwik.mjs",
      "displayName": "Link_component_a_onQVisible",
      "canonicalFilename": "s_uve5im9h73c",
      "hash": "uVE5iM9H73c",
      "ctxKind": "event",
      "ctxName": "onQVisible$",
      "captures": false,
      "parent": "s_mYsiJcA4IBc"
    },
    "s_AaAlzKH0KlQ": {
      "origin": "../node_modules/@builder.io/qwik-city/index.qwik.mjs",
      "displayName": "QwikCity_component_useWatch",
      "canonicalFilename": "s_aaalzkh0klq",
      "hash": "AaAlzKH0KlQ",
      "ctxKind": "function",
      "ctxName": "useWatch$",
      "captures": true,
      "parent": "s_z1nvHyEppoI"
    },
    "s_FKfJcKag6gA": {
      "origin": "components/cards/standard-card.tsx",
      "displayName": "standard_card_component",
      "canonicalFilename": "s_fkfjckag6ga",
      "hash": "FKfJcKag6gA",
      "ctxKind": "function",
      "ctxName": "component$",
      "captures": false
    },
    "s_H1DCWNWGDs0": {
      "origin": "root.tsx",
      "displayName": "root_component",
      "canonicalFilename": "s_h1dcwnwgds0",
      "hash": "H1DCWNWGDs0",
      "ctxKind": "function",
      "ctxName": "component$",
      "captures": false
    },
    "s_IJFWOVOMv2k": {
      "origin": "routes/site/index.tsx",
      "displayName": "site_component",
      "canonicalFilename": "s_ijfwovomv2k",
      "hash": "IJFWOVOMv2k",
      "ctxKind": "function",
      "ctxName": "component$",
      "captures": false
    },
    "s_IOeCWCVMsYo": {
      "origin": "components/footer/footer.tsx",
      "displayName": "footer_component",
      "canonicalFilename": "s_ioecwcvmsyo",
      "hash": "IOeCWCVMsYo",
      "ctxKind": "function",
      "ctxName": "component$",
      "captures": false
    },
    "s_USHQYhRQTrM": {
      "origin": "routes/index .tsx",
      "displayName": "index__component",
      "canonicalFilename": "s_ushqyhrqtrm",
      "hash": "USHQYhRQTrM",
      "ctxKind": "function",
      "ctxName": "component$",
      "captures": false
    },
    "s_VkTVgkSdmLs": {
      "origin": "components/router-head/router-head.tsx",
      "displayName": "RouterHead_component",
      "canonicalFilename": "s_vktvgksdmls",
      "hash": "VkTVgkSdmLs",
      "ctxKind": "function",
      "ctxName": "component$",
      "captures": false
    },
    "s_c1z6q2id8HY": {
      "origin": "routes/layout.tsx",
      "displayName": "layout_component",
      "canonicalFilename": "s_c1z6q2id8hy",
      "hash": "c1z6q2id8HY",
      "ctxKind": "function",
      "ctxName": "component$",
      "captures": false
    },
    "s_eiL3jn9IT8E": {
      "origin": "routes/hikers_app/index.tsx",
      "displayName": "hikers_app_component",
      "canonicalFilename": "s_eil3jn9it8e",
      "hash": "eiL3jn9IT8E",
      "ctxKind": "function",
      "ctxName": "component$",
      "captures": false
    },
    "s_eq0fQikduZU": {
      "origin": "components/cards/project-card.tsx",
      "displayName": "project_card_component",
      "canonicalFilename": "s_eq0fqikduzu",
      "hash": "eq0fQikduZU",
      "ctxKind": "function",
      "ctxName": "component$",
      "captures": false
    },
    "s_hnjgsKzLBow": {
      "origin": "components/project_info_site/project-info-site.tsx",
      "displayName": "project_info_site_component",
      "canonicalFilename": "s_hnjgskzlbow",
      "hash": "hnjgsKzLBow",
      "ctxKind": "function",
      "ctxName": "component$",
      "captures": false
    },
    "s_mTY0EDyooQc": {
      "origin": "components/gallery/gallery.tsx",
      "displayName": "gallery_component",
      "canonicalFilename": "s_mty0edyooqc",
      "hash": "mTY0EDyooQc",
      "ctxKind": "function",
      "ctxName": "component$",
      "captures": false
    },
    "s_mYsiJcA4IBc": {
      "origin": "../node_modules/@builder.io/qwik-city/index.qwik.mjs",
      "displayName": "Link_component",
      "canonicalFilename": "s_mysijca4ibc",
      "hash": "mYsiJcA4IBc",
      "ctxKind": "function",
      "ctxName": "component$",
      "captures": false
    },
    "s_nd8yk3KO22c": {
      "origin": "../node_modules/@builder.io/qwik-city/index.qwik.mjs",
      "displayName": "RouterOutlet_component",
      "canonicalFilename": "s_nd8yk3ko22c",
      "hash": "nd8yk3KO22c",
      "ctxKind": "function",
      "ctxName": "component$",
      "captures": false
    },
    "s_qQceZbtLrN0": {
      "origin": "routes/cv/index.tsx",
      "displayName": "cv_component",
      "canonicalFilename": "s_qqcezbtlrn0",
      "hash": "qQceZbtLrN0",
      "ctxKind": "function",
      "ctxName": "component$",
      "captures": false
    },
    "s_qSYXU2ks8ac": {
      "origin": "components/timeline/timeline.tsx",
      "displayName": "timeline_component",
      "canonicalFilename": "s_qsyxu2ks8ac",
      "hash": "qSYXU2ks8ac",
      "ctxKind": "function",
      "ctxName": "component$",
      "captures": false
    },
    "s_y9blzKaITCg": {
      "origin": "components/title-catcher/title-catcher.tsx",
      "displayName": "title_catcher_component",
      "canonicalFilename": "s_y9blzkaitcg",
      "hash": "y9blzKaITCg",
      "ctxKind": "function",
      "ctxName": "component$",
      "captures": false
    },
    "s_z1nvHyEppoI": {
      "origin": "../node_modules/@builder.io/qwik-city/index.qwik.mjs",
      "displayName": "QwikCity_component",
      "canonicalFilename": "s_z1nvhyeppoi",
      "hash": "z1nvHyEppoI",
      "ctxKind": "function",
      "ctxName": "component$",
      "captures": false
    },
    "s_0T5Wt0KXY8Q": {
      "origin": "routes/index .tsx",
      "displayName": "index__component_useStylesScoped",
      "canonicalFilename": "s_0t5wt0kxy8q",
      "hash": "0T5Wt0KXY8Q",
      "ctxKind": "function",
      "ctxName": "useStylesScoped$",
      "captures": false,
      "parent": "s_USHQYhRQTrM"
    },
    "s_BE1hF2Pw9l0": {
      "origin": "components/title-catcher/title-catcher.tsx",
      "displayName": "title_catcher_component_useStylesScoped",
      "canonicalFilename": "s_be1hf2pw9l0",
      "hash": "BE1hF2Pw9l0",
      "ctxKind": "function",
      "ctxName": "useStylesScoped$",
      "captures": false,
      "parent": "s_y9blzKaITCg"
    },
    "s_MgUPZePdpaY": {
      "origin": "components/gallery/gallery.tsx",
      "displayName": "gallery_component_useStylesScoped",
      "canonicalFilename": "s_mgupzepdpay",
      "hash": "MgUPZePdpaY",
      "ctxKind": "function",
      "ctxName": "useStylesScoped$",
      "captures": false,
      "parent": "s_mTY0EDyooQc"
    },
    "s_a0nBubIIWWY": {
      "origin": "components/footer/footer.tsx",
      "displayName": "footer_component_useStylesScoped",
      "canonicalFilename": "s_a0nbubiiwwy",
      "hash": "a0nBubIIWWY",
      "ctxKind": "function",
      "ctxName": "useStylesScoped$",
      "captures": false,
      "parent": "s_IOeCWCVMsYo"
    },
    "s_kUnjeesoBsc": {
      "origin": "components/project_info_site/project-info-site.tsx",
      "displayName": "project_info_site_component_useStylesScoped",
      "canonicalFilename": "s_kunjeesobsc",
      "hash": "kUnjeesoBsc",
      "ctxKind": "function",
      "ctxName": "useStylesScoped$",
      "captures": false,
      "parent": "s_hnjgsKzLBow"
    },
    "s_mUvfeoW6R1g": {
      "origin": "components/cards/project-card.tsx",
      "displayName": "project_card_component_useStylesScoped",
      "canonicalFilename": "s_muvfeow6r1g",
      "hash": "mUvfeoW6R1g",
      "ctxKind": "function",
      "ctxName": "useStylesScoped$",
      "captures": false,
      "parent": "s_eq0fQikduZU"
    },
    "s_oBizoPJXxws": {
      "origin": "components/cards/standard-card.tsx",
      "displayName": "standard_card_component_useStylesScoped",
      "canonicalFilename": "s_obizopjxxws",
      "hash": "oBizoPJXxws",
      "ctxKind": "function",
      "ctxName": "useStylesScoped$",
      "captures": false,
      "parent": "s_FKfJcKag6gA"
    },
    "s_sS53USNbJNA": {
      "origin": "components/timeline/timeline.tsx",
      "displayName": "timeline_component_useStylesScoped",
      "canonicalFilename": "s_ss53usnbjna",
      "hash": "sS53USNbJNA",
      "ctxKind": "function",
      "ctxName": "useStylesScoped$",
      "captures": false,
      "parent": "s_qSYXU2ks8ac"
    }
  },
  "mapping": {
    "s_hA9UPaY8sNQ": "q-fcff6781.js",
    "s_skxgNVWVOT8": "q-fcff6781.js",
    "s_uVE5iM9H73c": "q-fcff6781.js",
    "s_AaAlzKH0KlQ": "q-4975cda0.js",
    "s_FKfJcKag6gA": "q-0e140fec.js",
    "s_H1DCWNWGDs0": "q-7439bb29.js",
    "s_IJFWOVOMv2k": "q-4d066ebb.js",
    "s_IOeCWCVMsYo": "q-2812e18f.js",
    "s_USHQYhRQTrM": "q-578d7086.js",
    "s_VkTVgkSdmLs": "q-7a459830.js",
    "s_c1z6q2id8HY": "q-009913bd.js",
    "s_eiL3jn9IT8E": "q-40306db0.js",
    "s_eq0fQikduZU": "q-5c0ceed2.js",
    "s_hnjgsKzLBow": "q-182ef574.js",
    "s_mTY0EDyooQc": "q-72b20c3c.js",
    "s_mYsiJcA4IBc": "q-fcff6781.js",
    "s_nd8yk3KO22c": "q-562bb612.js",
    "s_qQceZbtLrN0": "q-81f3cf2b.js",
    "s_qSYXU2ks8ac": "q-d216730e.js",
    "s_y9blzKaITCg": "q-4f21b9dc.js",
    "s_z1nvHyEppoI": "q-4975cda0.js",
    "s_0T5Wt0KXY8Q": "q-578d7086.js",
    "s_BE1hF2Pw9l0": "q-4f21b9dc.js",
    "s_MgUPZePdpaY": "q-72b20c3c.js",
    "s_a0nBubIIWWY": "q-2812e18f.js",
    "s_kUnjeesoBsc": "q-182ef574.js",
    "s_mUvfeoW6R1g": "q-5c0ceed2.js",
    "s_oBizoPJXxws": "q-0e140fec.js",
    "s_sS53USNbJNA": "q-d216730e.js"
  },
  "bundles": {
    "q-009913bd.js": {
      "size": 270,
      "imports": [
        "q-99b26040.js"
      ],
      "dynamicImports": [
        "q-2812e18f.js"
      ],
      "origins": [
        "src/components/footer/footer.js",
        "src/entry_layout.js",
        "src/s_c1z6q2id8hy.js"
      ],
      "symbols": [
        "s_c1z6q2id8HY"
      ]
    },
    "q-069390e2.js": {
      "size": 58,
      "imports": [
        "q-99b26040.js"
      ]
    },
    "q-0e140fec.js": {
      "size": 669,
      "imports": [
        "q-99b26040.js"
      ],
      "origins": [
        "src/components/cards/standard-card.css?used&inline",
        "src/entry_standard_card.js",
        "src/s_fkfjckag6ga.js",
        "src/s_obizopjxxws.js"
      ],
      "symbols": [
        "s_FKfJcKag6gA",
        "s_oBizoPJXxws"
      ]
    },
    "q-182ef574.js": {
      "size": 1338,
      "imports": [
        "q-99b26040.js"
      ],
      "dynamicImports": [
        "q-72b20c3c.js"
      ],
      "origins": [
        "src/components/gallery/gallery.js",
        "src/components/project_info_site/project-info-site.css?used&inline",
        "src/entry_project_info_site.js",
        "src/s_hnjgskzlbow.js",
        "src/s_kunjeesobsc.js"
      ],
      "symbols": [
        "s_hnjgsKzLBow",
        "s_kUnjeesoBsc"
      ]
    },
    "q-1b403312.js": {
      "size": 158,
      "imports": [
        "q-99b26040.js"
      ],
      "dynamicImports": [
        "q-009913bd.js"
      ],
      "origins": [
        "src/routes/layout.js"
      ]
    },
    "q-1c35958c.js": {
      "size": 152,
      "imports": [
        "q-99b26040.js"
      ],
      "dynamicImports": [
        "q-182ef574.js"
      ],
      "origins": [
        "src/components/project_info_site/project-info-site.js"
      ]
    },
    "q-1c77786e.js": {
      "size": 185,
      "imports": [
        "q-99b26040.js"
      ],
      "dynamicImports": [
        "q-81f3cf2b.js"
      ],
      "origins": [
        "src/routes/cv/index.js"
      ]
    },
    "q-1dd5e43f.js": {
      "size": 2536,
      "origins": [
        "node_modules/@builder.io/qwik-city/service-worker.mjs",
        "src/routes/service-worker.js"
      ]
    },
    "q-2812e18f.js": {
      "size": 1103,
      "imports": [
        "q-99b26040.js"
      ],
      "origins": [
        "src/components/footer/footer.css?used&inline",
        "src/entry_footer.js",
        "src/s_a0nbubiiwwy.js",
        "src/s_ioecwcvmsyo.js"
      ],
      "symbols": [
        "s_a0nBubIIWWY",
        "s_IOeCWCVMsYo"
      ]
    },
    "q-40306db0.js": {
      "size": 1137,
      "imports": [
        "q-1c35958c.js",
        "q-99b26040.js"
      ],
      "origins": [
        "src/entry_hikers_app.js",
        "src/s_eil3jn9it8e.js"
      ],
      "symbols": [
        "s_eiL3jn9IT8E"
      ]
    },
    "q-4975cda0.js": {
      "size": 1489,
      "imports": [
        "q-7439bb29.js",
        "q-99b26040.js"
      ],
      "dynamicImports": [
        "q-e9894559.js"
      ],
      "origins": [
        "@builder.io/qwik/build",
        "src/entry_QwikCity.js",
        "src/s_aaalzkh0klq.js",
        "src/s_z1nvhyeppoi.js"
      ],
      "symbols": [
        "s_AaAlzKH0KlQ",
        "s_z1nvHyEppoI"
      ]
    },
    "q-4d066ebb.js": {
      "size": 740,
      "imports": [
        "q-1c35958c.js",
        "q-99b26040.js"
      ],
      "origins": [
        "src/entry_site.js",
        "src/s_ijfwovomv2k.js"
      ],
      "symbols": [
        "s_IJFWOVOMv2k"
      ]
    },
    "q-4f21b9dc.js": {
      "size": 640,
      "imports": [
        "q-99b26040.js"
      ],
      "origins": [
        "src/components/title-catcher/title-catcher.css?used&inline",
        "src/entry_title_catcher.js",
        "src/s_be1hf2pw9l0.js",
        "src/s_y9blzkaitcg.js"
      ],
      "symbols": [
        "s_BE1hF2Pw9l0",
        "s_y9blzKaITCg"
      ]
    },
    "q-562bb612.js": {
      "size": 269,
      "imports": [
        "q-7439bb29.js",
        "q-99b26040.js"
      ],
      "origins": [
        "src/entry_RouterOutlet.js",
        "src/s_nd8yk3ko22c.js"
      ],
      "symbols": [
        "s_nd8yk3KO22c"
      ]
    },
    "q-578d7086.js": {
      "size": 2670,
      "imports": [
        "q-99b26040.js"
      ],
      "dynamicImports": [
        "q-0e140fec.js",
        "q-4f21b9dc.js",
        "q-5c0ceed2.js"
      ],
      "origins": [
        "src/components/cards/project-card.js",
        "src/components/cards/standard-card.js",
        "src/components/title-catcher/title-catcher.js",
        "src/entry_index_.js",
        "src/routes/index.css?used&inline",
        "src/s_0t5wt0kxy8q.js",
        "src/s_ushqyhrqtrm.js"
      ],
      "symbols": [
        "s_0T5Wt0KXY8Q",
        "s_USHQYhRQTrM"
      ]
    },
    "q-5c0ceed2.js": {
      "size": 1465,
      "imports": [
        "q-99b26040.js"
      ],
      "origins": [
        "src/components/cards/project-card.css?used&inline",
        "src/entry_project_card.js",
        "src/s_eq0fqikduzu.js",
        "src/s_muvfeow6r1g.js"
      ],
      "symbols": [
        "s_eq0fQikduZU",
        "s_mUvfeoW6R1g"
      ]
    },
    "q-6a0b01ff.js": {
      "size": 185,
      "imports": [
        "q-99b26040.js"
      ],
      "dynamicImports": [
        "q-578d7086.js"
      ],
      "origins": [
        "src/routes/index .js"
      ]
    },
    "q-72b20c3c.js": {
      "size": 977,
      "imports": [
        "q-99b26040.js"
      ],
      "origins": [
        "src/components/gallery/gallery.css?used&inline",
        "src/entry_gallery.js",
        "src/s_mgupzepdpay.js",
        "src/s_mty0edyooqc.js"
      ],
      "symbols": [
        "s_MgUPZePdpaY",
        "s_mTY0EDyooQc"
      ]
    },
    "q-7439bb29.js": {
      "size": 4159,
      "imports": [
        "q-99b26040.js"
      ],
      "dynamicImports": [
        "q-4975cda0.js",
        "q-562bb612.js",
        "q-7a459830.js",
        "q-fcff6781.js"
      ],
      "origins": [
        "node_modules/@builder.io/qwik-city/index.qwik.mjs",
        "src/components/router-head/router-head.js",
        "src/entry_root.js",
        "src/s_h1dcwnwgds0.js"
      ],
      "symbols": [
        "s_H1DCWNWGDs0"
      ]
    },
    "q-7a459830.js": {
      "size": 878,
      "imports": [
        "q-7439bb29.js",
        "q-99b26040.js"
      ],
      "origins": [
        "src/entry_RouterHead.js",
        "src/s_vktvgksdmls.js"
      ],
      "symbols": [
        "s_VkTVgkSdmLs"
      ]
    },
    "q-81f3cf2b.js": {
      "size": 424,
      "imports": [
        "q-99b26040.js"
      ],
      "dynamicImports": [
        "q-d216730e.js"
      ],
      "origins": [
        "src/components/timeline/timeline.js",
        "src/entry_cv.js",
        "src/s_qqcezbtlrn0.js"
      ],
      "symbols": [
        "s_qQceZbtLrN0"
      ]
    },
    "q-99b26040.js": {
      "size": 39971,
      "dynamicImports": [
        "q-7439bb29.js"
      ],
      "origins": [
        "\u0000vite/preload-helper",
        "node_modules/@builder.io/qwik/core.min.mjs",
        "src/global.css",
        "src/root.js"
      ]
    },
    "q-a92a27f5.js": {
      "size": 128,
      "imports": [
        "q-99b26040.js"
      ],
      "dynamicImports": [
        "q-1dd5e43f.js"
      ],
      "origins": [
        "@qwik-city-entries"
      ]
    },
    "q-b05d731b.js": {
      "size": 180,
      "imports": [
        "q-99b26040.js"
      ],
      "dynamicImports": [
        "q-4d066ebb.js"
      ],
      "origins": [
        "src/routes/site/index.js"
      ]
    },
    "q-d216730e.js": {
      "size": 1122,
      "imports": [
        "q-99b26040.js"
      ],
      "origins": [
        "src/components/timeline/timeline.css?used&inline",
        "src/entry_timeline.js",
        "src/s_qsyxu2ks8ac.js",
        "src/s_ss53usnbjna.js"
      ],
      "symbols": [
        "s_qSYXU2ks8ac",
        "s_sS53USNbJNA"
      ]
    },
    "q-e9894559.js": {
      "size": 573,
      "imports": [
        "q-99b26040.js"
      ],
      "dynamicImports": [
        "q-1b403312.js",
        "q-1c77786e.js",
        "q-6a0b01ff.js",
        "q-a92a27f5.js",
        "q-b05d731b.js",
        "q-e9d812e5.js"
      ],
      "origins": [
        "@qwik-city-plan"
      ]
    },
    "q-e9d812e5.js": {
      "size": 185,
      "imports": [
        "q-99b26040.js"
      ],
      "dynamicImports": [
        "q-40306db0.js"
      ],
      "origins": [
        "src/routes/hikers_app/index.js"
      ]
    },
    "q-fcff6781.js": {
      "size": 886,
      "imports": [
        "q-7439bb29.js",
        "q-99b26040.js"
      ],
      "origins": [
        "src/entry_Link.js",
        "src/s_ha9upay8snq.js",
        "src/s_mysijca4ibc.js",
        "src/s_skxgnvwvot8.js",
        "src/s_uve5im9h73c.js"
      ],
      "symbols": [
        "s_hA9UPaY8sNQ",
        "s_mYsiJcA4IBc",
        "s_skxgNVWVOT8",
        "s_uVE5iM9H73c"
      ]
    }
  },
  "injections": [
    {
      "tag": "link",
      "location": "head",
      "attributes": {
        "rel": "stylesheet",
        "href": "/build/q-3bbce4cb.css"
      }
    }
  ],
  "version": "1",
  "options": {
    "target": "client",
    "buildMode": "production",
    "forceFullBuild": true,
    "entryStrategy": {
      "type": "smart"
    }
  },
  "platform": {
    "qwik": "0.11.1",
    "vite": "",
    "rollup": "2.78.1",
    "env": "node",
    "os": "linux",
    "node": "16.18.1"
  }
}